<?xml version='1.0' encoding='utf-8'?>
<manuscript id="210">
   <identifier libraryID="london_bl">
      <shelfmark>Sloane MS 1044 (fol. 3)</shelfmark>
   </identifier>
   <description>
      <type />
      <folios>1</folios>
      <page_h>6.5</page_h>
      <page_w>22</page_w>
      <contents>Gregory the Great, <i>Dialogi</i> (3.31–32)</contents>
      <script>Insular majuscule</script>
   </description>
   <history>
      <date_desc>VIII²</date_desc>
      <term_post>751</term_post>
      <term_ante>800</term_ante>
      <origin><place id="ireland">Ireland</place></origin>
   </history>
   <refs>
      <canonical corresp="#cla" href="https://elmss.nuigalway.ie/catalogue/536"><i>CLA</i> 2.218</canonical>
      <canonical href="https://www.trismegistos.org/text/66316">TM 66316</canonical>
   </refs>
   <notes categories="#or-ire #sc-ire">
   </notes>
   <revisionDesc>
      <change who="Pádraic Moran" when="2021-05-01">Created</change>
   </revisionDesc>
</manuscript>